pysdbapi/__init__.py
pysdbapi/exceptions.py
pysdbapi/main.py
pysdbapi/type_hints/__init__.py
pysdbapi/type_hints/alias.py
pysdbapi/type_hints/type_vars.py
pysdbapi/utils.py
pysdbapi-0.5.0.dist-info/LICENSE
pysdbapi-0.5.0.dist-info/WHEEL
pysdbapi-0.5.0.dist-info/METADATA
pysdbapi-0.5.0.dist-info/RECORD
