Metadata-Version: 2.1
Name: pysdbapi
Version: 0.5.0
Summary: pySDBAPI - simple database API. Use a couple of lines to make a request
Home-page: https://github.com/axemanofic/pysdbapi
License: MIT
Keywords: python,database,prettytable
Author: Roman
Author-email: axeman.ofic@gmail.com
Maintainer: Roman
Maintainer-email: axeman.ofic@gmail.com
Requires-Python: >=3.10,<4.0
Classifier: Development Status :: 5 - Production/Stable
Classifier: License :: OSI Approved :: MIT License
Classifier: Programming Language :: Python :: 3
Classifier: Programming Language :: Python :: 3.10
Classifier: Programming Language :: Python :: 3.11
Provides-Extra: pretty
Requires-Dist: prettytable (>=3.5.0,<4.0.0); extra == "pretty"
Project-URL: Repository, https://github.com/axemanofic/pysdbapi
